citrouille/__init__.py
citrouille/cli.py
citrouille/comparator.py
citrouille/config.py
citrouille/formatters.py
citrouille/kube_client.py
citrouille/security_checks/__init__.py
citrouille/security_checks/check_01_privileged_containers.py
citrouille/security_checks/check_02_host_pid.py
citrouille/security_checks/check_03_host_ipc.py
citrouille/security_checks/check_04_host_network.py
citrouille/security_checks/check_05_run_as_root.py
citrouille/security_checks/check_06_privilege_escalation.py
citrouille/security_checks/check_07_capabilities.py
citrouille/security_checks/check_08_resource_limits.py
citrouille/security_checks/check_09_host_path.py
citrouille/security_checks/check_10_readonly_filesystem.py
citrouille/security_checks/check_11_seccomp.py
citrouille/security_checks/check_12_service_account_token.py
citrouille/security_checks/check_13_image_tags.py
citrouille/security_checks/check_14_hardcoded_secrets.py
citrouille/security_checks/check_15_pss_enforcement.py
citrouille/security_checks/check_16_immutable_config.py
citrouille/security_checks/check_17_emptydir_limits.py
citrouille/security_checks/check_18_proc_mount.py
citrouille/security_checks/check_19_rbac_roles.py
citrouille/security_checks/check_20_rbac_bindings.py
citrouille/security_checks/check_21_shared_process_ns.py
citrouille/security_checks/check_22_sysctls.py
citrouille/security_checks/check_23_network_policies.py
citrouille-1.1.2.dist-info/licenses/LICENSE
citrouille-1.1.2.dist-info/METADATA
citrouille-1.1.2.dist-info/WHEEL
citrouille-1.1.2.dist-info/entry_points.txt
citrouille-1.1.2.dist-info/top_level.txt
citrouille-1.1.2.dist-info/RECORD
