Metadata-Version: 2.4
Name: citrouille
Version: 1.1.2
Summary: CLI tool to identify security issues on Kubernetes at the deployment level, compare namespaces for green/blue cycles, and reduce time-to-recovery 
Author-email: Chelsea486MHz <mail@chelsea486mhz.fr>
License:                     GNU GENERAL PUBLIC LICENSE
Project-URL: Repository, https://github.com/Chelsea486MHz/citrouille
Project-URL: Issues, https://github.com/Chelsea486MHz/citrouille/issues
Keywords: kubernetes,devops,devsecops,seceng,secops
Classifier: Development Status :: 5 - Production/Stable
Classifier: Environment :: Console
Classifier: Intended Audience :: Developers
Classifier: Intended Audience :: System Administrators
Classifier: License :: OSI Approved :: GNU General Public License v3 (GPLv3)
Classifier: Natural Language :: English
Classifier: Operating System :: OS Independent
Classifier: Topic :: Security
Classifier: Topic :: Software Development :: Quality Assurance
Classifier: Topic :: System :: Systems Administration
Requires-Python: >=3.12
License-File: LICENSE
Requires-Dist: kubernetes>=34.1.0
Requires-Dist: pyyaml>=6.0.3
Dynamic: license-file
